Metadata-Version: 2.1
Name: devtools_text_diff
Version: 1.0.1
Summary: Text diff tool
Home-page: https://devtools.at/tools/text-diff
Author: DevTools.at
Author-email: hello@devtools.at
Project-URL: Homepage, https://devtools.at/tools/text-diff
Project-URL: Repository, https://github.com/devtools-at/text-diff
Classifier: Development Status :: 4 - Beta
Classifier: Intended Audience :: Developers
Classifier: License :: OSI Approved :: MIT License
Classifier: Programming Language :: Python :: 3
Requires-Python: >=3.8
